{"anchor_date":"2026-07-14","content_hash":"06474177e8ecb7d951ecd70fcfb7e1131e6c8878bb8c07b57664febc2c1128c9","generated_at":"2026-07-14T01:03:37Z","manifest_id":"a030a9ad-2813-513c-83e3-214c05cde0c0","model":{"feature_store_hash":null,"name":"lgbm_growth_smallcap","training_data_cutoff":null,"version":"1.0_production"},"original_event_date":"2020-07-01","positions":[{"entry_price":15.024,"model_score":null,"rank_in_universe":1,"shares":120.59869150715167,"ticker":"LRCX","weight":0.03819492},{"entry_price":20.88,"model_score":null,"rank_in_universe":2,"shares":206.1905531378129,"ticker":"MTOR","weight":0.03912244},{"entry_price":53.62,"model_score":null,"rank_in_universe":3,"shares":50.17417125533368,"ticker":"NXST","weight":0.04165379},{"entry_price":12.98,"model_score":null,"rank_in_universe":4,"shares":275.1901335391425,"ticker":"HRB","weight":0.03843329},{"entry_price":68.28,"model_score":null,"rank_in_universe":5,"shares":34.379963836567384,"ticker":"LGND","weight":0.03838141},{"entry_price":73.36,"model_score":null,"rank_in_universe":6,"shares":37.759821686551234,"ticker":"CBRL","weight":0.04117151},{"entry_price":420.4,"model_score":null,"rank_in_universe":7,"shares":9.945478417764935,"ticker":"CACC","weight":0.04170951},{"entry_price":20.1,"model_score":null,"rank_in_universe":8,"shares":189.20519473581464,"ticker":"KSS","weight":0.03793812},{"entry_price":68.7,"model_score":null,"rank_in_universe":9,"shares":54.576563692318565,"ticker":"EMN","weight":0.03740327},{"entry_price":75.35,"model_score":null,"rank_in_universe":10,"shares":51.183852480828904,"ticker":"ABG","weight":0.0384736},{"entry_price":16.42,"model_score":null,"rank_in_universe":11,"shares":259.7289706914045,"ticker":"NCLH","weight":0.04254418},{"entry_price":76.11,"model_score":null,"rank_in_universe":12,"shares":52.03418979326575,"ticker":"DRI","weight":0.03950728},{"entry_price":34.45,"model_score":null,"rank_in_universe":13,"shares":117.62783402995353,"ticker":"UAL","weight":0.04042462},{"entry_price":141.27,"model_score":null,"rank_in_universe":14,"shares":27.16515919778167,"ticker":"MED","weight":0.03828325},{"entry_price":35.7,"model_score":null,"rank_in_universe":15,"shares":105.17670843583946,"ticker":"ALK","weight":0.03745713},{"entry_price":73.79,"model_score":null,"rank_in_universe":16,"shares":56.4201376163275,"ticker":"WYNN","weight":0.04153157},{"entry_price":134.12,"model_score":null,"rank_in_universe":17,"shares":28.187941425375424,"ticker":"SNA","weight":0.03771408},{"entry_price":63.64,"model_score":null,"rank_in_universe":18,"shares":64.33834767905944,"ticker":"GPI","weight":0.04084574},{"entry_price":39.09,"model_score":null,"rank_in_universe":19,"shares":97.23152546469865,"ticker":"PAG","weight":0.03791573},{"entry_price":26.34,"model_score":null,"rank_in_universe":20,"shares":143.09075376422703,"ticker":"XEC","weight":0.0375988},{"entry_price":23.41,"model_score":null,"rank_in_universe":21,"shares":169.38859932218398,"ticker":"AMCX","weight":0.03955781},{"entry_price":106.21,"model_score":null,"rank_in_universe":22,"shares":38.58202034084643,"ticker":"LEA","weight":0.0408787},{"entry_price":190.32,"model_score":null,"rank_in_universe":23,"shares":19.924121042171002,"ticker":"CVCO","weight":0.03782773},{"entry_price":28.32,"model_score":null,"rank_in_universe":24,"shares":134.80157615205573,"ticker":"AL","weight":0.03808333},{"entry_price":15.34,"model_score":null,"rank_in_universe":25,"shares":249.00644503536486,"ticker":"CPRI","weight":0.03810506}],"prev_manifest_hash":"03c5e0d367fa4cf9af8eda13f49384506965eb4b06f8641173aacad2969d3fad","rationale":{"market_narrative":null,"performance_evaluation":null,"portfolio_evaluation":null,"regime_evaluation":null,"sector_evaluation":null},"regime":{"probability_vector":{},"state_label":"unknown"},"retroactive":true,"run_type":"backfill_historical","schema_version":"1.0.0","strategy_id":"growth_smallcap","strategy_name":"Small-Mid Cap Growth","stream":"equity"}