{"anchor_date":"2026-07-14","content_hash":"f8dc293df849ad2bd6b0ab4fec392c9e86984a87e979ff3cc66b0819a0727e1e","generated_at":"2026-07-14T01:03:37Z","manifest_id":"636972dd-578a-55f8-bf3b-7c4f93353c1f","model":{"feature_store_hash":null,"name":"lgbm_value","training_data_cutoff":null,"version":"1.0_production"},"original_event_date":"2022-07-01","positions":[{"entry_price":26.536,"model_score":null,"rank_in_universe":1,"shares":161.12587030215158,"ticker":"TSCO","weight":0.03994988},{"entry_price":46.44,"model_score":null,"rank_in_universe":2,"shares":151.6276678139919,"ticker":"WMT","weight":0.03914102},{"entry_price":348.92,"model_score":null,"rank_in_universe":3,"shares":30.22211200117663,"ticker":"BIIB","weight":0.0401997},{"entry_price":56.01,"model_score":null,"rank_in_universe":4,"shares":176.7063661342871,"ticker":"INTC","weight":0.04055225},{"entry_price":41.43,"model_score":null,"rank_in_universe":5,"shares":213.44932393396326,"ticker":"ENVA","weight":0.03976442},{"entry_price":84.435,"model_score":null,"rank_in_universe":6,"shares":109.38549559346748,"ticker":"WSM","weight":0.03896325},{"entry_price":15.14,"model_score":null,"rank_in_universe":7,"shares":493.1196794920198,"ticker":"TTMI","weight":0.03789839},{"entry_price":61.41,"model_score":null,"rank_in_universe":8,"shares":107.07638153462153,"ticker":"ECPG","weight":0.03978051},{"entry_price":50.52,"model_score":null,"rank_in_universe":9,"shares":168.0713674797029,"ticker":"OMF","weight":0.0408738},{"entry_price":106.0225,"model_score":null,"rank_in_universe":10,"shares":63.60373432396871,"ticker":"CTAS","weight":0.03782749},{"entry_price":28.4,"model_score":null,"rank_in_universe":11,"shares":272.7807659552682,"ticker":"VIRT","weight":0.04020614},{"entry_price":27.47,"model_score":null,"rank_in_universe":12,"shares":224.95904297088006,"ticker":"BKE","weight":0.03902473},{"entry_price":34.2,"model_score":null,"rank_in_universe":13,"shares":175.36699325556904,"ticker":"ALLY","weight":0.03787492},{"entry_price":54.07,"model_score":null,"rank_in_universe":14,"shares":110.73556473284911,"ticker":"FAF","weight":0.03781127},{"entry_price":39.22,"model_score":null,"rank_in_universe":15,"shares":157.19170710460074,"ticker":"AVNT","weight":0.03893275},{"entry_price":26.41,"model_score":null,"rank_in_universe":16,"shares":242.36857182759795,"ticker":"MLKN","weight":0.04042244},{"entry_price":92.43,"model_score":null,"rank_in_universe":17,"shares":65.54011744646238,"ticker":"SNX","weight":0.03825586},{"entry_price":16.92,"model_score":null,"rank_in_universe":18,"shares":366.68807828003406,"ticker":"NMIH","weight":0.03918095},{"entry_price":66.77,"model_score":null,"rank_in_universe":19,"shares":95.44850303685007,"ticker":"BBY","weight":0.04024652},{"entry_price":37.69,"model_score":null,"rank_in_universe":20,"shares":162.78738118928845,"ticker":"FNF","weight":0.0387458},{"entry_price":14.523,"model_score":null,"rank_in_universe":21,"shares":428.3009536305066,"ticker":"NVDA","weight":0.03928106},{"entry_price":44.56,"model_score":null,"rank_in_universe":22,"shares":142.84928426000158,"ticker":"MCY","weight":0.04019769},{"entry_price":35.9,"model_score":null,"rank_in_universe":23,"shares":168.2269645653656,"ticker":"APAM","weight":0.03813887},{"entry_price":157.59,"model_score":null,"rank_in_universe":24,"shares":38.21102212829395,"ticker":"WHR","weight":0.03802727},{"entry_price":19.51,"model_score":null,"rank_in_universe":25,"shares":318.79834365025164,"ticker":"NWL","weight":0.03927816}],"prev_manifest_hash":"46cbae71108a99172ce614f59fd3f039aa1a86330b0fa8eed9dfa9db935223b8","rationale":{"market_narrative":null,"performance_evaluation":null,"portfolio_evaluation":null,"regime_evaluation":null,"sector_evaluation":null},"regime":{"probability_vector":{"momentum_score":-0.00208,"predicted_max_drawdown_60d":-0.160151,"predicted_spy_return_60d":-0.022912,"predicted_value_minus_growth_60d":-0.00208,"predicted_vol_expansion_60d":0.888292,"regime_intensity":0.5,"risk_on_score":-0.022912},"state_label":"defensive_rotation"},"retroactive":true,"run_type":"backfill_historical","schema_version":"1.0.0","strategy_id":"value","strategy_name":"Value Investing","stream":"equity"}