{"anchor_date":"2026-07-14","content_hash":"5f68ce102876efc64e9c169944602e747f10753ba5eb72fb67bacf11975ab060","generated_at":"2026-07-14T01:03:37Z","manifest_id":"fdf79c8d-149f-5658-9b03-75c310325864","model":{"feature_store_hash":null,"name":"lgbm_value","training_data_cutoff":null,"version":"1.0_production"},"original_event_date":"2024-01-02","positions":[{"entry_price":28.4,"model_score":null,"rank_in_universe":1,"shares":410.8283426673789,"ticker":"VIRT","weight":0.03860751},{"entry_price":47.21,"model_score":null,"rank_in_universe":2,"shares":148.9895642963304,"ticker":"SAH","weight":0.03861872},{"entry_price":12.81,"model_score":null,"rank_in_universe":3,"shares":641.9848897626509,"ticker":"SBH","weight":0.03940005},{"entry_price":20.13,"model_score":null,"rank_in_universe":4,"shares":432.98810698168364,"ticker":"M","weight":0.03951026},{"entry_price":179.16,"model_score":null,"rank_in_universe":5,"shares":27.56633990987815,"ticker":"GPI","weight":0.03882629},{"entry_price":32.73,"model_score":null,"rank_in_universe":6,"shares":232.0651548333241,"ticker":"LAZ","weight":0.03870835},{"entry_price":167.12,"model_score":null,"rank_in_universe":7,"shares":53.82251219500443,"ticker":"NXST","weight":0.03982242},{"entry_price":76.24,"model_score":null,"rank_in_universe":8,"shares":96.02477662778874,"ticker":"CCS","weight":0.03947904},{"entry_price":35.36,"model_score":null,"rank_in_universe":9,"shares":236.69290414960463,"ticker":"ALLY","weight":0.03864955},{"entry_price":67.575,"model_score":null,"rank_in_universe":10,"shares":126.68035229468724,"ticker":"RLI","weight":0.03953141},{"entry_price":34.15,"model_score":null,"rank_in_universe":11,"shares":249.04386825039032,"ticker":"TPH","weight":0.03927476},{"entry_price":37.96,"model_score":null,"rank_in_universe":12,"shares":223.07849182587256,"ticker":"SYF","weight":0.03910487},{"entry_price":13.23,"model_score":null,"rank_in_universe":13,"shares":655.7241449041933,"ticker":"LAUR","weight":0.04006157},{"entry_price":12.13,"model_score":null,"rank_in_universe":14,"shares":710.2909166618789,"ticker":"WU","weight":0.03978726},{"entry_price":21.49,"model_score":null,"rank_in_universe":15,"shares":398.6795383853893,"ticker":"MGY","weight":0.03956465},{"entry_price":101.655,"model_score":null,"rank_in_universe":16,"shares":85.78124258459002,"ticker":"WSM","weight":0.04026874},{"entry_price":49.57,"model_score":null,"rank_in_universe":17,"shares":168.66785452034762,"ticker":"FNF","weight":0.03860986},{"entry_price":49.4,"model_score":null,"rank_in_universe":18,"shares":173.5602055239162,"ticker":"OMF","weight":0.03959351},{"entry_price":44.15,"model_score":null,"rank_in_universe":19,"shares":190.4888597939236,"ticker":"OVV","weight":0.03883714},{"entry_price":82.08,"model_score":null,"rank_in_universe":20,"shares":101.80890110315711,"ticker":"BPOP","weight":0.03858958},{"entry_price":51.32,"model_score":null,"rank_in_universe":21,"shares":161.43598021201322,"ticker":"ETR","weight":0.03825903},{"entry_price":36.84,"model_score":null,"rank_in_universe":22,"shares":232.418296270197,"ticker":"NOG","weight":0.03954002},{"entry_price":51.25,"model_score":null,"rank_in_universe":23,"shares":171.32597122625583,"ticker":"NRG","weight":0.04054749},{"entry_price":52.75,"model_score":null,"rank_in_universe":24,"shares":159.067389146192,"ticker":"KLIC","weight":0.03874811},{"entry_price":87.9,"model_score":null,"rank_in_universe":25,"shares":95.42130640193047,"ticker":"NNI","weight":0.038733}],"prev_manifest_hash":"ad4ac21b38df732df3c09b8d0bb28a5164860649417b4d3cfa8e1a2942703a06","rationale":{"market_narrative":null,"performance_evaluation":null,"portfolio_evaluation":null,"regime_evaluation":null,"sector_evaluation":null},"regime":{"probability_vector":{"momentum_score":-0.067281,"predicted_max_drawdown_60d":-0.11603,"predicted_spy_return_60d":-0.049906,"predicted_value_minus_growth_60d":-0.067281,"predicted_vol_expansion_60d":1.351572,"regime_intensity":0.5,"risk_on_score":-0.049906},"state_label":"risk_on_stable"},"retroactive":true,"run_type":"backfill_historical","schema_version":"1.0.0","strategy_id":"value","strategy_name":"Value Investing","stream":"equity"}